odoo/addons/stock_pull_list/README.rst
odoo/addons/stock_pull_list/__init__.py
odoo/addons/stock_pull_list/__manifest__.py
odoo/addons/stock_pull_list/i18n/stock_pull_list.pot
odoo/addons/stock_pull_list/readme/CONTRIBUTORS.rst
odoo/addons/stock_pull_list/readme/DESCRIPTION.rst
odoo/addons/stock_pull_list/readme/ROADMAP.rst
odoo/addons/stock_pull_list/readme/USAGE.rst
odoo/addons/stock_pull_list/static/description/icon.png
odoo/addons/stock_pull_list/static/description/index.html
odoo/addons/stock_pull_list/tests/__init__.py
odoo/addons/stock_pull_list/tests/common.py
odoo/addons/stock_pull_list/tests/test_stock_pull_list.py
odoo/addons/stock_pull_list/wizards/__init__.py
odoo/addons/stock_pull_list/wizards/stock_pull_list_wizard.py
odoo/addons/stock_pull_list/wizards/stock_pull_list_wizard.xml
odoo12_addon_stock_pull_list-12.0.1.0.1.dist-info/METADATA
odoo12_addon_stock_pull_list-12.0.1.0.1.dist-info/WHEEL
odoo12_addon_stock_pull_list-12.0.1.0.1.dist-info/top_level.txt
odoo12_addon_stock_pull_list-12.0.1.0.1.dist-info/RECORD
