Metadata-Version: 2.1
Name: odoo12-addon-stock-pull-list
Version: 12.0.1.0.1
Summary: The pull list checks the stock situation and calculates needed quantities.
Home-page: https://github.com/OCA/stock-logistics-warehouse
Author: ForgeFlow, Odoo Community Association (OCA)
Author-email: support@odoo-community.org
License: LGPL-3
Platform: UNKNOWN
Classifier: Programming Language :: Python
Classifier: Framework :: Odoo
Classifier: License :: OSI Approved :: GNU Lesser General Public License v3 (LGPLv3)
Classifier: Development Status :: 3 - Alpha
Requires-Python: >=3.5
Requires-Dist: odoo12-addon-stock-available-unreserved
Requires-Dist: odoo (<12.1dev,>=12.0a)
